[
  {
    "is_synthetic_slot": false,
    "is_tbd": false,
    "_id": 15631370,
    "__v": 0,
    "away_team": {
      "id": 2836,
      "name": "Atlético Madrid",
      "score": 2
    },
    "createdAt": "2026-04-13T23:31:01.491Z",
    "home_team": {
      "id": 33,
      "name": "Tottenham Hotspur",
      "score": 3
    },
    "startTimestamp": 1773864000,
    "status": {
      "code": 100,
      "description": "Ended",
      "type": "finished"
    },
    "tournament_id": 7,
    "tournament_name": "Champions League",
    "updatedAt": "2026-06-10T05:33:08.047Z",
    "awayScore": {
      "current": 2,
      "display": 2,
      "period1": 0,
      "period2": 2,
      "normaltime": 2,
      "aggregated": 7
    },
    "backfill_date": "2026-04-14T03:54:19.810Z",
    "homeScore": {
      "current": 3,
      "display": 3,
      "period1": 1,
      "period2": 2,
      "normaltime": 3,
      "aggregated": 5
    }
  },
  {
    "is_synthetic_slot": false,
    "is_tbd": false,
    "_id": 15631356,
    "__v": 0,
    "away_team": {
      "id": 33,
      "name": "Tottenham Hotspur",
      "score": 2
    },
    "createdAt": "2026-04-13T23:31:01.491Z",
    "home_team": {
      "id": 2836,
      "name": "Atlético Madrid",
      "score": 5
    },
    "startTimestamp": 1773172800,
    "status": {
      "code": 100,
      "description": "Ended",
      "type": "finished"
    },
    "tournament_id": 7,
    "tournament_name": "Champions League",
    "updatedAt": "2026-06-10T05:33:08.047Z",
    "awayScore": {
      "current": 2,
      "display": 2,
      "period1": 1,
      "period2": 1,
      "normaltime": 2
    },
    "backfill_date": "2026-04-14T03:46:17.453Z",
    "homeScore": {
      "current": 5,
      "display": 5,
      "period1": 4,
      "period2": 1,
      "normaltime": 5
    }
  }
]